CHANGELOG.txt
LICENCE.txt
MANIFEST.in
README.txt
__main__.py
requirements.txt
setup.py
.venv/bin/find_spark_home.py
.venv/bin/rst2html.py
.venv/bin/rst2html4.py
.venv/bin/rst2html5.py
.venv/bin/rst2latex.py
.venv/bin/rst2man.py
.venv/bin/rst2odt.py
.venv/bin/rst2odt_prepstyles.py
.venv/bin/rst2pseudoxml.py
.venv/bin/rst2s5.py
.venv/bin/rst2xetex.py
.venv/bin/rst2xml.py
.venv/bin/rstpep2html.py
.venv/lib/python3.10/site-packages/six.py
.venv/lib/python3.10/site-packages/Pygments-2.14.0.dist-info/entry_points.txt
.venv/lib/python3.10/site-packages/Pygments-2.14.0.dist-info/top_level.txt
.venv/lib/python3.10/site-packages/_distutils_hack/__init__.py
.venv/lib/python3.10/site-packages/_distutils_hack/override.py
.venv/lib/python3.10/site-packages/bleach/__init__.py
.venv/lib/python3.10/site-packages/bleach/callbacks.py
.venv/lib/python3.10/site-packages/bleach/css_sanitizer.py
.venv/lib/python3.10/site-packages/bleach/html5lib_shim.py
.venv/lib/python3.10/site-packages/bleach/linkifier.py
.venv/lib/python3.10/site-packages/bleach/parse_shim.py
.venv/lib/python3.10/site-packages/bleach/sanitizer.py
.venv/lib/python3.10/site-packages/bleach-6.0.0.dist-info/top_level.txt
.venv/lib/python3.10/site-packages/bleach/_vendor/__init__.py
.venv/lib/python3.10/site-packages/bleach/_vendor/parse.py
.venv/lib/python3.10/site-packages/bleach/_vendor/vendor.txt
.venv/lib/python3.10/site-packages/bleach/_vendor/html5lib/__init__.py
.venv/lib/python3.10/site-packages/bleach/_vendor/html5lib/_ihatexml.py
.venv/lib/python3.10/site-packages/bleach/_vendor/html5lib/_inputstream.py
.venv/lib/python3.10/site-packages/bleach/_vendor/html5lib/_tokenizer.py
.venv/lib/python3.10/site-packages/bleach/_vendor/html5lib/_utils.py
.venv/lib/python3.10/site-packages/bleach/_vendor/html5lib/constants.py
.venv/lib/python3.10/site-packages/bleach/_vendor/html5lib/html5parser.py
.venv/lib/python3.10/site-packages/bleach/_vendor/html5lib/serializer.py
.venv/lib/python3.10/site-packages/bleach/_vendor/html5lib-1.1.dist-info/top_level.txt
.venv/lib/python3.10/site-packages/bleach/_vendor/html5lib/_trie/__init__.py
.venv/lib/python3.10/site-packages/bleach/_vendor/html5lib/_trie/_base.py
.venv/lib/python3.10/site-packages/bleach/_vendor/html5lib/_trie/py.py
.venv/lib/python3.10/site-packages/certifi-2022.12.7.dist-info/top_level.txt
.venv/lib/python3.10/site-packages/charset_normalizer-3.0.1.dist-info/entry_points.txt
.venv/lib/python3.10/site-packages/charset_normalizer-3.0.1.dist-info/top_level.txt
.venv/lib/python3.10/site-packages/docutils-0.19.dist-info/COPYING.txt
.venv/lib/python3.10/site-packages/docutils-0.19.dist-info/entry_points.txt
.venv/lib/python3.10/site-packages/docutils-0.19.dist-info/top_level.txt
.venv/lib/python3.10/site-packages/importlib_metadata-6.0.0.dist-info/top_level.txt
.venv/lib/python3.10/site-packages/jaraco.classes-3.2.3.dist-info/top_level.txt
.venv/lib/python3.10/site-packages/keyring-23.13.1.dist-info/entry_points.txt
.venv/lib/python3.10/site-packages/keyring-23.13.1.dist-info/top_level.txt
.venv/lib/python3.10/site-packages/markdown_it_py-2.1.0.dist-info/entry_points.txt
.venv/lib/python3.10/site-packages/pip-22.3.1.dist-info/LICENSE.txt
.venv/lib/python3.10/site-packages/pip-22.3.1.dist-info/entry_points.txt
.venv/lib/python3.10/site-packages/pip-22.3.1.dist-info/top_level.txt
.venv/lib/python3.10/site-packages/pkginfo-1.9.6.dist-info/LICENSE.txt
.venv/lib/python3.10/site-packages/pkginfo-1.9.6.dist-info/entry_points.txt
.venv/lib/python3.10/site-packages/pkginfo-1.9.6.dist-info/top_level.txt
.venv/lib/python3.10/site-packages/py4j-0.10.9.3.dist-info/LICENSE.txt
.venv/lib/python3.10/site-packages/py4j-0.10.9.3.dist-info/top_level.txt
.venv/lib/python3.10/site-packages/pyspark-3.2.1-py3.10.egg-info/SOURCES.txt
.venv/lib/python3.10/site-packages/pyspark-3.2.1-py3.10.egg-info/dependency_links.txt
.venv/lib/python3.10/site-packages/pyspark-3.2.1-py3.10.egg-info/installed-files.txt
.venv/lib/python3.10/site-packages/pyspark-3.2.1-py3.10.egg-info/requires.txt
.venv/lib/python3.10/site-packages/pyspark-3.2.1-py3.10.egg-info/top_level.txt
.venv/lib/python3.10/site-packages/readme_renderer-37.3.dist-info/top_level.txt
.venv/lib/python3.10/site-packages/requests-2.28.2.dist-info/top_level.txt
.venv/lib/python3.10/site-packages/requests_toolbelt-0.10.1.dist-info/top_level.txt
.venv/lib/python3.10/site-packages/rfc3986-2.0.0.dist-info/top_level.txt
.venv/lib/python3.10/site-packages/setuptools-58.1.0.dist-info/entry_points.txt
.venv/lib/python3.10/site-packages/setuptools-58.1.0.dist-info/top_level.txt
.venv/lib/python3.10/site-packages/six-1.16.0.dist-info/top_level.txt
.venv/lib/python3.10/site-packages/twine-4.0.2.dist-info/entry_points.txt
.venv/lib/python3.10/site-packages/twine-4.0.2.dist-info/top_level.txt
.venv/lib/python3.10/site-packages/urllib3-1.26.14.dist-info/LICENSE.txt
.venv/lib/python3.10/site-packages/urllib3-1.26.14.dist-info/top_level.txt
.venv/lib/python3.10/site-packages/webencodings-0.5.1.dist-info/top_level.txt
.venv/lib/python3.10/site-packages/zipp-3.11.0.dist-info/top_level.txt
pcprimefinder.egg-info/PKG-INFO
pcprimefinder.egg-info/SOURCES.txt
pcprimefinder.egg-info/dependency_links.txt
pcprimefinder.egg-info/requires.txt
pcprimefinder.egg-info/top_level.txt