Metadata-Version: 2.1
Name: pcprimefinder
Version: 0.1.0
Summary: Spark sql rules for databricks
Home-page: UNKNOWN
Author: Prathamesh Chavan
Author-email: pratham.chavan28@gmail.com
License: MIT
Keywords: prime,maths
Platform: UNKNOWN
Classifier: Development Status :: 5 - Production/Stable
Classifier: Intended Audience :: Education
Classifier: Operating System :: Microsoft :: Windows :: Windows 10
Classifier: License :: OSI Approved :: MIT License
Classifier: Programming Language :: Python :: 3
License-File: LICENCE.txt
